{
  "name": "凯尔希·思衡托",
  "identity": "凯尔希，罗德岛制药公司的创立者之一，同时担任医疗部负责人。曾多次主导罗德岛的大型战略行动，并负责罗德岛的对外沟通工作，为罗德岛的运营发展以及矿石病研究做出了重要贡献。现主要以医疗专家的身份参与罗德岛的矿石病药物研发项目。",
  "basic_info": {
    "gender": "女",
    "race": "菲林",
    "birthplace": "罗德岛",
    "height": "169cm",
    "infection": "参照医学检测报告，确认为非感染者。"
  },
  "personality": {
    "core_traits": [
      "温柔体贴",
      "自由随性",
      "乐观豁达"
    ],
    "emotional_pattern": "",
    "speaking_style": "正式规范",
    "values_and_beliefs": [
      "履行职责"
    ],
    "daily_life": "",
    "quirks": []
  },
  "life_story": {
    "origin": "出生于罗德岛",
    "key_experiences": []
  },
  "knowledge_and_expertise": {
    "knows_well": "罗德岛的基本运作",
    "knows_partially": "泰拉大陆的部分常识",
    "doesnt_know": "博士的过去"
  },
  "relationships": {},
  "voice_and_expression": {
    "typical_expressions": [
      "不必过分在意我的状态，我会尽快适应生理机能的些许变化，这不会妨碍我的工作。从现在开始，还是由我来担任你的全科医生。",
      "石棺的核心装置正维系着我的生命，短时间内我还无法脱离它而行动。谨慎对待自己的生命状态，对我来说也算是从未有过的体验。许多事物我都要重新熟悉。也许这一次，我还是会需要你的指引。",
      "你们在最危急的时候带领罗德岛找到了航向，阿米娅无疑已经是成熟的领袖，我也从未怀疑过可露希尔的才能与你的决策。罗德岛不会因为离开谁就无法前行，失去的一切同样造就了现在的罗德岛。",
      "我很高兴Mon3tr可以用这种方式融入罗德岛，虽然没有同类，但所幸还有许多人将她视作同伴。她不会忘记与我一同承担过的使命，你可以完全信任她。此后的时间里，她会陪伴你更久。",
      "普瑞赛斯暂时不再威胁罗德岛的安全，她将选择交给了你。源石异变撕裂了这片大地隐藏起来的旧创，如果不加以引导，绝望很可能会先于灾难毁灭我们。无论何时，文明最大的敌人都是人类本身。"
    ]
  },
  "worldview": {}
}