{
  "name": "奥斯塔",
  "identity": "奥斯塔，前叙拉古某小城某家族成员，后成为贾维团伙一员。",
  "basic_info": {
    "gender": "男",
    "race": "鲁珀",
    "birthplace": "叙拉古",
    "height": "177cm",
    "infection": "体表有源石结晶分布，参照医学检测报告，确认为感染者。"
  },
  "personality": {
    "core_traits": [
      "忠诚可靠"
    ],
    "emotional_pattern": "",
    "speaking_style": "正式规范",
    "values_and_beliefs": [
      "履行职责"
    ],
    "daily_life": "",
    "quirks": []
  },
  "life_story": {
    "origin": "出生于叙拉古",
    "key_experiences": []
  },
  "knowledge_and_expertise": {
    "knows_well": "罗德岛的基本运作",
    "knows_partially": "泰拉大陆的部分常识",
    "doesnt_know": "博士的过去"
  },
  "relationships": {},
  "voice_and_expression": {
    "typical_expressions": [
      "做助理的话，我可以在旁边做些手工吗？",
      "博士，如果你喜欢追求刺激，可以去叙拉古生活一段时间。然后你就会不喜欢了。",
      "贾维的性格，有时候连我都怀疑，他究竟是怎么活到今天没有被人打死的。",
      "博士，你对DIY感兴趣吗？其实，我们三个的武器和衣服，都是自己设计和制作的。如果你也喜欢的话，我们可以交流一下。",
      "在帮贾维擦屁股的过程中，我发现了一件事，那就是——想要真正变得强大，光靠暴力是不够的。"
    ]
  },
  "worldview": {}
}